Metadata-Version: 2.1
Name: joshcustom-probability
Version: 1.1
Summary: Gaussian and Binomial distributions
Home-page: UNKNOWN
Author: Owoicho Joshua Odinya
Author-email: owoichojoshuaodinya@gmail.com
License: UNKNOWN
Platform: UNKNOWN
